DADMSPeakSolver/__init__.py
DADMSPeakSolver/combine_ms_dad.py
DADMSPeakSolver/create_file.py
DADMSPeakSolver/dad_spectra_comparison.py
DADMSPeakSolver/data_processing.py
DADMSPeakSolver/data_processing_dad.py
DADMSPeakSolver/databank_handling.py
DADMSPeakSolver/initialize.py
DADMSPeakSolver/main.py
DADMSPeakSolver/ms_deconvolution.py
DADMSPeakSolver/ms_spectra_comparison.py
DADMSPeakSolver/ms_superimposed_peaks.py
DADMSPeakSolver/optimization_script.py
DADMSPeakSolver/output.py
DADMSPeakSolver/output_analytics.py
DADMSPeakSolver/output_files.py
DADMSPeakSolver/output_visualization.py
DADMSPeakSolver/runs_handling.py
DADMSPeakSolver/signal_peak_handling.py
DADMSPeakSolver/mocca/__init__.py
DADMSPeakSolver/mocca/py.typed
DADMSPeakSolver/mocca/campaign/__init__.py
DADMSPeakSolver/mocca/campaign/experiment_funcs.py
DADMSPeakSolver/mocca/campaign/process_funcs.py
DADMSPeakSolver/mocca/campaign/utils.py
DADMSPeakSolver/mocca/chromatogram/__init__.py
DADMSPeakSolver/mocca/chromatogram/assign.py
DADMSPeakSolver/mocca/chromatogram/correct.py
DADMSPeakSolver/mocca/chromatogram/model.py
DADMSPeakSolver/mocca/chromatogram/preprocessor.py
DADMSPeakSolver/mocca/chromatogram/quantify.py
DADMSPeakSolver/mocca/chromatogram/utils.py
DADMSPeakSolver/mocca/components/__init__.py
DADMSPeakSolver/mocca/components/databases.py
DADMSPeakSolver/mocca/components/models.py
DADMSPeakSolver/mocca/components/quali_funcs.py
DADMSPeakSolver/mocca/components/quant_funcs.py
DADMSPeakSolver/mocca/components/utils.py
DADMSPeakSolver/mocca/dad_data/__init__.py
DADMSPeakSolver/mocca/dad_data/models.py
DADMSPeakSolver/mocca/dad_data/process_funcs.py
DADMSPeakSolver/mocca/dad_data/process_gradientdata.py
DADMSPeakSolver/mocca/dad_data/utils.py
DADMSPeakSolver/mocca/dad_data/apis/__init__.py
DADMSPeakSolver/mocca/dad_data/apis/allotrope.py
DADMSPeakSolver/mocca/dad_data/apis/angi.py
DADMSPeakSolver/mocca/dad_data/apis/chemstation.py
DADMSPeakSolver/mocca/dad_data/apis/custom.py
DADMSPeakSolver-0.1.15.dist-info/LICENSE
DADMSPeakSolver-0.1.15.dist-info/METADATA
DADMSPeakSolver-0.1.15.dist-info/WHEEL
DADMSPeakSolver-0.1.15.dist-info/top_level.txt
DADMSPeakSolver-0.1.15.dist-info/RECORD
